docify/__init__.py
docifyPLUS/__init__.py
DocifyPLUS-1.0.0.dist-info/LICENSE
DocifyPLUS-1.0.0.dist-info/METADATA
DocifyPLUS-1.0.0.dist-info/WHEEL
DocifyPLUS-1.0.0.dist-info/top_level.txt
DocifyPLUS-1.0.0.dist-info/RECORD
